paas_app_charmer/__init__.py
paas_app_charmer/django/__init__.py
paas_app_charmer/django/charm.py
paas_app_charmer/fastapi/__init__.py
paas_app_charmer/fastapi/charm.py
paas_app_charmer/flask/__init__.py
paas_app_charmer/flask/charm.py
paas_app_charmer/go/__init__.py
paas_app_charmer/go/charm.py
paas_charm/__init__.py
paas_charm/app.py
paas_charm/charm.py
paas_charm/charm_state.py
paas_charm/charm_utils.py
paas_charm/database_migration.py
paas_charm/databases.py
paas_charm/exceptions.py
paas_charm/framework.py
paas_charm/http_proxy.py
paas_charm/oauth.py
paas_charm/observability.py
paas_charm/openfga.py
paas_charm/rabbitmq.py
paas_charm/redis.py
paas_charm/s3.py
paas_charm/saml.py
paas_charm/secret_storage.py
paas_charm/tracing.py
paas_charm/utils.py
paas_charm/_gunicorn/__init__.py
paas_charm/_gunicorn/charm.py
paas_charm/_gunicorn/webserver.py
paas_charm/_gunicorn/workload_config.py
paas_charm/_gunicorn/wsgi_app.py
paas_charm/django/__init__.py
paas_charm/django/charm.py
paas_charm/django/cos/grafana_dashboards/django.json
paas_charm/django/cos/loki_alert_rules/.gitkeep
paas_charm/django/cos/prometheus_alert_rules/django.rule
paas_charm/expressjs/__init__.py
paas_charm/expressjs/charm.py
paas_charm/expressjs/cos/grafana_dashboards/expressjs.json
paas_charm/expressjs/cos/loki_alert_rules/.gitkeep
paas_charm/expressjs/cos/prometheus_alert_rules/.gitkeep
paas_charm/fastapi/__init__.py
paas_charm/fastapi/charm.py
paas_charm/fastapi/cos/grafana_dashboards/fastapi.json
paas_charm/fastapi/cos/loki_alert_rules/.gitkeep
paas_charm/fastapi/cos/prometheus_alert_rules/.gitkeep
paas_charm/flask/__init__.py
paas_charm/flask/charm.py
paas_charm/flask/cos/grafana_dashboards/flask.json
paas_charm/flask/cos/loki_alert_rules/.gitkeep
paas_charm/flask/cos/prometheus_alert_rules/flask.rule
paas_charm/go/__init__.py
paas_charm/go/charm.py
paas_charm/go/cos/grafana_dashboards/go.json
paas_charm/go/cos/loki_alert_rules/.gitkeep
paas_charm/go/cos/prometheus_alert_rules/.gitkeep
paas_charm-1.9.1.dist-info/METADATA
paas_charm-1.9.1.dist-info/WHEEL
paas_charm-1.9.1.dist-info/top_level.txt
paas_charm-1.9.1.dist-info/RECORD
