Metadata-Version: 2.4
Name: paas-charm
Version: 1.9.1
Summary: Companion library for 12-factor app support in Charmcraft & Rockcraft.
Author-email: Canonical IS DevOps team <is-devops-team@canonical.com>
Project-URL: Repository, https://github.com/canonical/paas-charm
Classifier: Development Status :: 5 - Production/Stable
Classifier: Intended Audience :: Developers
Classifier: License :: OSI Approved :: Apache Software License
Classifier: Operating System :: OS Independent
Classifier: Programming Language :: Python :: 3
Requires-Python: >=3.10
Requires-Dist: cosl
Requires-Dist: Jinja2==3.1.6
Requires-Dist: jsonschema<4.26,>=4.25
Requires-Dist: ops>=2.6
Requires-Dist: pydantic==2.11.9
